yowasp_yosys/__init__.py
yowasp_yosys/sby.py
yowasp_yosys/smtbmc.py
yowasp_yosys/witness.py
yowasp_yosys/yosys.wasm
yowasp_yosys/share/abc9_map.v
yowasp_yosys/share/abc9_model.v
yowasp_yosys/share/abc9_unmap.v
yowasp_yosys/share/adff2dff.v
yowasp_yosys/share/cmp2lcu.v
yowasp_yosys/share/cmp2lut.v
yowasp_yosys/share/cmp2softlogic.v
yowasp_yosys/share/dff2ff.v
yowasp_yosys/share/gate2lut.v
yowasp_yosys/share/mul2dsp.v
yowasp_yosys/share/pmux2mux.v
yowasp_yosys/share/simcells.v
yowasp_yosys/share/simlib.v
yowasp_yosys/share/smtmap.v
yowasp_yosys/share/techmap.v
yowasp_yosys/share/achronix/speedster22i/cells_map.v
yowasp_yosys/share/achronix/speedster22i/cells_sim.v
yowasp_yosys/share/anlogic/arith_map.v
yowasp_yosys/share/anlogic/brams.txt
yowasp_yosys/share/anlogic/brams_map.v
yowasp_yosys/share/anlogic/cells_map.v
yowasp_yosys/share/anlogic/cells_sim.v
yowasp_yosys/share/anlogic/eagle_bb.v
yowasp_yosys/share/anlogic/lutrams.txt
yowasp_yosys/share/anlogic/lutrams_map.v
yowasp_yosys/share/choices/han-carlson.v
yowasp_yosys/share/choices/kogge-stone.v
yowasp_yosys/share/choices/sklansky.v
yowasp_yosys/share/coolrunner2/cells_counter_map.v
yowasp_yosys/share/coolrunner2/cells_latch.v
yowasp_yosys/share/coolrunner2/cells_sim.v
yowasp_yosys/share/coolrunner2/tff_extract.v
yowasp_yosys/share/coolrunner2/xc2_dff.lib
yowasp_yosys/share/ecp5/ccu2c_sim.vh
yowasp_yosys/share/ecp5/cells_bb.v
yowasp_yosys/share/ecp5/cells_ff.vh
yowasp_yosys/share/ecp5/cells_io.vh
yowasp_yosys/share/ecp5/cells_sim.v
yowasp_yosys/share/ecp5/common_sim.vh
yowasp_yosys/share/efinix/arith_map.v
yowasp_yosys/share/efinix/brams.txt
yowasp_yosys/share/efinix/brams_map.v
yowasp_yosys/share/efinix/cells_map.v
yowasp_yosys/share/efinix/cells_sim.v
yowasp_yosys/share/efinix/gbuf_map.v
yowasp_yosys/share/fabulous/arith_map.v
yowasp_yosys/share/fabulous/cells_map.v
yowasp_yosys/share/fabulous/ff_map.v
yowasp_yosys/share/fabulous/io_map.v
yowasp_yosys/share/fabulous/latches_map.v
yowasp_yosys-0.60.0.0.post1055.dist-info/METADATA
yowasp_yosys-0.60.0.0.post1055.dist-info/WHEEL
yowasp_yosys-0.60.0.0.post1055.dist-info/entry_points.txt
yowasp_yosys-0.60.0.0.post1055.dist-info/top_level.txt
yowasp_yosys-0.60.0.0.post1055.dist-info/RECORD
