Metadata-Version: 2.4
Name: yowasp-yosys
Version: 0.60.0.0.post1055
Summary: Yosys Open SYnthesis Suite
Author-email: Catherine <whitequark@whitequark.org>
License-Expression: ISC
Project-URL: Homepage, https://yowasp.org/
Project-URL: Source Code, https://github.com/YoWASP/yosys
Project-URL: Bug Tracker, https://github.com/YoWASP/yosys/issues
Requires-Python: ~=3.9
Requires-Dist: yowasp-runtime~=1.12
Requires-Dist: click
